{
"insectes": [
	{ "genere":"Acherontia" , "especie":"atropos" },
	{ "genere":"Acmaeodera" , "especie":"rubromaculata" },
	{ "genere":"Adalia" , "especie":"decempunctata" },
	{ "genere":"Adela" , "especie":"australis" },
	{ "genere":"Adelphocoris" , "especie":"vandalicus" },
	{ "genere":"Adonia" , "especie":"variegata" },
	{ "genere":"Agrypnus" , "especie":"murinus" },
	{ "genere":"Akis" , "especie":"tuberculata" },
	{ "genere":"Ameles" , "especie":"spallanzania" },
	{ "genere":"Anastoechus" , "especie":"nitidulus" },
	{ "genere":"Anatis" , "especie":"ocellata" },
	{ "genere":"Ancylosis" , "especie":"cinnamomella" },
	{ "genere":"Anisops" , "especie":"sardea" },
	{ "genere":"Anthaxia" , "especie":"hungarica" },
	{ "genere":"Anthomyia" , "especie":"pluvialis" },
	{ "genere":"Apis" , "especie":"mellifera" },
	{ "genere":"Aporia" , "especie":"crataegi" },
	{ "genere":"Aquarius" , "especie":"paludum" },
	{ "genere":"Arachnocephalus" , "especie":"vestitus" },
	{ "genere":"Argiope" , "especie":"bruennichi" },
	{ "genere":"Argynnis" , "especie":"aglaja" },
	{ "genere":"Argynnis" , "especie":"paphia" },
	{ "genere":"Atlantoraphidia" , "especie":"maculicollis" },
	{ "genere":"Berosus" , "especie":"hispanicus" },
	{ "genere":"Bibio" , "especie":"hortulanus" },
	{ "genere":"Blaps" , "especie":"gigas" },
	{ "genere":"Blatta" , "especie":"orientalis" },
	{ "genere":"Bombylella" , "especie":"atra" },
	{ "genere":"Bombylius" , "especie":"cruciatus" },
	{ "genere":"Brintesia" , "especie":"circe" },
	{ "genere":"Cacoecimorpha" , "especie":"pronubana" },
	{ "genere":"Callimorpha" , "especie":"dominula" },
	{ "genere":"Calopterix" , "especie":"haemorrhoidalis" },
	{ "genere":"Camponotus" , "especie":"cruentatus" },
	{ "genere":"Carcharodus" , "especie":"alceae" },
	{ "genere":"Carpocoris" , "especie":"fuscispinus" },
	{ "genere":"Carpocoris" , "especie":"mediterraneus" },
	{ "genere":"Carpocoris" , "especie":"pudicus" },
	{ "genere":"Carpocoris" , "especie":"purpureipennis" },
	{ "genere":"Cercopis" , "especie":"intermedia" },
	{ "genere":"Ceriagrion" , "especie":"tenellum" },
	{ "genere":"Chalcophora" , "especie":"mariana" },
	{ "genere":"Charaxes" , "especie":"jasius" },
	{ "genere":"Chilocorus" , "especie":"bipustulatus" },
	{ "genere":"Chlorophorus" , "especie":"trifasciatus" },
	{ "genere":"Chlorophorus" , "especie":"varius" },
	{ "genere":"Chrysolina" , "especie":"herbacea" },
	{ "genere":"Chrysoperla" , "especie":"carnea" },
	{ "genere":"Cicada" , "especie":"barbara" },
	{ "genere":"Cicadella" , "especie":"viridis" },
	{ "genere":"Cicindela" , "especie":"maroccana" },
	{ "genere":"Cidnopus" , "especie":"pilosus" },
	{ "genere":"Cionus" , "especie":"hortulanus" },
	{ "genere":"Clytra" , "especie":"quadripunctata" },
	{ "genere":"Clytus" , "especie":"arietis" },
	{ "genere":"Coccinella" , "especie":"septempunctata" },
	{ "genere":"Codophila" , "especie":"varia" },
	{ "genere":"Coenagrion" , "especie":"mercuriale" },
	{ "genere":"Colias" , "especie":"alfacariensis" },
	{ "genere":"Colias" , "especie":"crocea" },
	{ "genere":"Colpa" , "especie":"sexmaculata" },
	{ "genere":"Copris" , "especie":"lunaris" },
	{ "genere":"Coranus" , "especie":"niger" },
	{ "genere":"Coreus" , "especie":"marginatus" },
	{ "genere":"Corizus" , "especie":"hyoscyami" },
	{ "genere":"Cryptocephalus" , "especie":"aureolus" },
	{ "genere":"Cryptocephalus" , "especie":"globicollis" },
	{ "genere":"Cryptocephalus" , "especie":"octoguttatus" },
	{ "genere":"Cryptocephalus" , "especie":"rugicollis" },
	{ "genere":"Cucullia (Shargacucullia)" , "especie":"lychnitis" },
	{ "genere":"Deraeocoris" , "especie":"ruber" },
	{ "genere":"Dermacentor" , "especie":"reticulatus" },
	{ "genere":"Dicladispa" , "especie":"testacea" },
	{ "genere":"Dicranocephalus" , "especie":"albipes" },
	{ "genere":"Dolycoris" , "especie":"baccarum" },
	{ "genere":"Dorcus" , "especie":"parallelipipedus" },
	{ "genere":"Dyscia" , "especie":"lentiscaria" },
	{ "genere":"Dysgonia" , "especie":"algira" },
	{ "genere":"Empis" , "especie":"sp" },
	{ "genere":"Empusa" , "especie":"pennata" },
	{ "genere":"Enoplops" , "especie":"scapha" },
	{ "genere":"Ephemera" , "especie":"vulgata" },
	{ "genere":"Ephippiger" , "especie":"ephippiger" },
	{ "genere":"Episyrphus" , "especie":"balteatus" },
	{ "genere":"Eristalinus" , "especie":"aeneus" },
	{ "genere":"Eristalis" , "especie":"arbustorum" },
	{ "genere":"Eumenes" , "especie":"Pomiformis" },
	{ "genere":"Eupeodes" , "especie":"corollae" },
	{ "genere":"Eurydema" , "especie":"ornata" },
	{ "genere":"Eurygaster" , "especie":"maura" },
	{ "genere":"Exosoma" , "especie":"lusitanicum" },
	{ "genere":"Forficula" , "especie":"auricularia" },
	{ "genere":"Gomphus" , "especie":"simillinus" },
	{ "genere":"Gonepteryx" , "especie":"cleopatra" },
	{ "genere":"Gonocerus" , "especie":"insidiator" },
	{ "genere":"Graphosoma" , "especie":"lineatum" },
	{ "genere":"Graphosoma" , "especie":"semipunctatum" },
	{ "genere":"Gryllus" , "especie":"campestris" },
	{ "genere":"Hadrodemus" , "especie":"m-flavum" },
	{ "genere":"Harmonia" , "especie":"axyridis conspicua" },
	{ "genere":"Harmonia" , "especie":"axyridis succinea" },
	{ "genere":"Hecatera" , "especie":"dysodea" },
	{ "genere":"Hemaris" , "especie":"fuciformis" },
	{ "genere":"Hesperia" , "especie":"comma" },
	{ "genere":"Hipparchia" , "especie":"alcyone" },
	{ "genere":"Hippobosca" , "especie":"equina" },
	{ "genere":"Hoplia" , "especie":"coerulea" },
	{ "genere":"Hydrometra" , "especie":"stagnorum" },
	{ "genere":"Hydrophorus" , "especie":"praecox" },
	{ "genere":"Hyles" , "especie":"euphorbiae" },
	{ "genere":"Hylotrupes" , "especie":"bajulus" },
	{ "genere":"Hysteropterum" , "especie":"sp" },
	{ "genere":"Idaea" , "especie":"consanguiberica" },
	{ "genere":"Inachis" , "especie":"io" },
	{ "genere":"Iphiclides" , "especie":"Podalirius" },
	{ "genere":"Lacon" , "especie":"punctatus" },
	{ "genere":"Lampyris" , "especie":"noctiluca" },
	{ "genere":"Lasiommata" , "especie":"megera" },
	{ "genere":"Lepisma" , "especie":"saccharina" },
	{ "genere":"Leptidea" , "especie":"sinapis" },
	{ "genere":"Leptinotarsa" , "especie":"decemlineata" },
	{ "genere":"Leptophyes" , "especie":"punctatissima" },
	{ "genere":"Lixus" , "especie":"cardui" },
	{ "genere":"Lixus" , "especie":"pulverulentus" },
	{ "genere":"Lycaena" , "especie":"phlaeas" },
	{ "genere":"Lycaena" , "especie":"virgaureae" },
	{ "genere":"Lygaeus" , "especie":"equestris" },
	{ "genere":"Macroglossum" , "especie":"stellatarum" },
	{ "genere":"Macronemurus" , "especie":"appendiculatus" },
	{ "genere":"Maniola" , "especie":"jurtina" },
	{ "genere":"Mantis" , "especie":"religiosa" },
	{ "genere":"Marianis" , "especie":"guapeta" },
	{ "genere":"Melanargia" , "especie":"galathea" },
	{ "genere":"Melanargia" , "especie":"lachesis" },
	{ "genere":"Melitaea" , "especie":"phoebe" },
	{ "genere":"Melitaea" , "especie":"trivia" },
	{ "genere":"Musca" , "especie":"domestica" },
	{ "genere":"Mylabris" , "especie":"quadripunctata" },
	{ "genere":"Mylabris" , "especie":"variabilis" },
	{ "genere":"Myrmeleon" , "especie":"gerlindae" },
	{ "genere":"Nemophora" , "especie":"metallica" },
	{ "genere":"Nezara" , "especie":"viridula" },
	{ "genere":"Ochterus" , "especie":"marginatus" },
	{ "genere":"Odontotarsus" , "especie":"purpureolineatus" },
	{ "genere":"Oedemera" , "especie":"femorata" },
	{ "genere":"Oedemera" , "especie":"flavipes" },
	{ "genere":"Oedipoda" , "especie":"caerulescens" },
	{ "genere":"Oedipoda" , "especie":"coerulea" },
	{ "genere":"Oenopia" , "especie":"conglobata" },
	{ "genere":"Oleracea" , "especie":"olearceum" },
	{ "genere":"Onychogomphus" , "especie":"forcipatus" },
	{ "genere":"Orphilus" , "especie":"niger" },
	{ "genere":"Orthetrum" , "especie":"coerulescenses" },
	{ "genere":"Oryctes" , "especie":"nasicornis" },
	{ "genere":"Osmylus" , "especie":"fulvicephalus" },
	{ "genere":"Oxythyrea" , "especie":"funesta" },
	{ "genere":"Palomena" , "especie":"prasina" },
	{ "genere":"Panorpa" , "especie":"communis" },
	{ "genere":"Papilio" , "especie":"machaon" },
	{ "genere":"Pararge" , "especie":"aegeria" },
	{ "genere":"Parnassius" , "especie":"apollo" },
	{ "genere":"Pediculus" , "especie":"humanus capitis" },
	{ "genere":"Petrus" , "especie":"sagalensis" },
	{ "genere":"Phaneroptera" , "especie":"nana" },
	{ "genere":"Phosphuga" , "especie":"atrata" },
	{ "genere":"Pieris" , "especie":"brassicae" },
	{ "genere":"Pieris" , "especie":"napi" },
	{ "genere":"Pieris" , "especie":"rapae" },
	{ "genere":"Plodia" , "especie":"interpunctella" },
	{ "genere":"Polistes" , "especie":"dominula" },
	{ "genere":"Polistes" , "especie":"nimpha" },
	{ "genere":"Polygonia" , "especie":"c-album" },
	{ "genere":"Polyommatus" , "especie":"icarus" },
	{ "genere":"Pontia" , "especie":"daplidice" },
	{ "genere":"Protaetia (Netocia)" , "especie":"morio" },
	{ "genere":"Pseudophilotes" , "especie":"panoptes" },
	{ "genere":"Pyralis" , "especie":"farinalis" },
	{ "genere":"Pyronia" , "especie":"cecilia" },
	{ "genere":"Pyronia" , "especie":"tithonus" },
	{ "genere":"Pyrrhocoris" , "especie":"apterus" },
	{ "genere":"Pyrrhosoma" , "especie":"nymphula" },
	{ "genere":"Reduvius" , "especie":"personatus" },
	{ "genere":"Rhagonycha" , "especie":"fulva" },
	{ "genere":"Sarcophaga" , "especie":"carnaria" },
	{ "genere":"Saturnia" , "especie":"pavonia" },
	{ "genere":"Satyrium" , "especie":"esculi" },
	{ "genere":"Scaurus" , "especie":"punctatus" },
	{ "genere":"Sermylassa" , "especie":"halensis" },
	{ "genere":"Sisyphus" , "especie":"schaefferi" },
	{ "genere":"Sphaerophoria" , "especie":"scripta" },
	{ "genere":"Sphinx" , "especie":"maurorum" },
	{ "genere":"Spialia" , "especie":"sertorius" },
	{ "genere":"Spilosoma" , "especie":"lubricipeda" },
	{ "genere":"Stenopterus" , "especie":"ater" },
	{ "genere":"Stenurella" , "especie":"melanura" },
	{ "genere":"Subcoccinella" , "especie":"24-punctata" },
	{ "genere":"Sympetrum" , "especie":"fonscolombii" },
	{ "genere":"Syromastus" , "especie":"rhombeus" },
	{ "genere":"Tettigonia" , "especie":"viridissima" },
	{ "genere":"Thaumetopoea" , "especie":"pityocampa" },
	{ "genere":"Thea" , "especie":"vigintiduopunctata" },
	{ "genere":"Timarcha" , "especie":"tenebricosa" },
	{ "genere":"Trichius" , "especie":"zonatus" },
	{ "genere":"Trichodes" , "especie":"apiarius" },
	{ "genere":"Trichodes" , "especie":"octopunctatus" },
	{ "genere":"Tritomegas" , "especie":"sexmaculatus" },
	{ "genere":"Tylopsis" , "especie":"lilifolia" },
	{ "genere":"Tytthaspis" , "especie":"sedecimpunctata" },
	{ "genere":"Uroleucon" , "especie":"sp" },
	{ "genere":"Vanessa" , "especie":"atalanta" },
	{ "genere":"Vanessa" , "especie":"cardui" },
	{ "genere":"Xanthogaleruca" , "especie":"luteola" },
	{ "genere":"Xylocopa" , "especie":"violacea" },
	{ "genere":"Zygaena" , "especie":"fausta" },
	{ "genere":"Zygaena" , "especie":"sarpedon" },
	{ "genere":"Zygaena" , "especie":"trifolii" }
]
}
